{
  "popular_cat": [
    {
      "title": "Двигатели",
      "img": "img/engine.png",
      "items": [
        {
          "text": "Cummins"
        },
        {
          "text": "Mercedes"
        },
        {
          "text": "ЯМЗ"
        },
        {
          "text": "ЗМЗ"
        },
        {
          "text": "ММЗ"
        }
      ]
    },
    {
      "title": "Сцепление",
      "img": "img/disks.png",
      "items": [
        {
          "text": "Готовые комплекты"
        },
        {
          "text": "Корзина сцепления"
        },
        {
          "text": "Диск сцепления"
        },
        {
          "text": "Подшипник выжимной"
        },
        {
          "text": "Смазки для шлицев"
        }
      ]
    },
    {
      "title": "Фильтры",
      "img": "img/filters.png",
      "items": [
        {
          "text": "Масляные          "
        },
        {
          "text": "Топливные          "
        },
        {
          "text": "Топлевные Сепараторы"
        },
        {
          "text": "Воздушные"
        },
        {
          "text": "Салонные"
        }
      ]
    },
    {
      "title": "Коробка передач",
      "img": "img/transmission.png",
      "items": [
        {
          "text": "Масляные          "
        },
        {
          "text": "Топливные          "
        },
        {
          "text": "Топлевные Сепараторы"
        },
        {
          "text": "Воздушные"
        },
        {
          "text": "Салонные"
        }
      ]
    },
    {
      "title": "Тормозные системы",
      "img": "img/disks.png",
      "items": [
        {
          "text": "Масляные          "
        },
        {
          "text": "Топливные          "
        },
        {
          "text": "Топлевные Сепараторы"
        },
        {
          "text": "Воздушные"
        },
        {
          "text": "Салонные"
        }
      ]
    },
    {
      "title": "Системы освещения",
      "img": "img/disks.png",
      "items": [
        {
          "text": "Масляные          "
        },
        {
          "text": "Топливные          "
        },
        {
          "text": "Топлевные Сепараторы"
        },
        {
          "text": "Воздушные"
        },
        {
          "text": "Салонные"
        }
      ]
    },
    {
      "title": "Детали экстерьера",
      "img": "img/accessories.png",
      "items": [
        {
          "text": "Масляные          "
        },
        {
          "text": "Топливные          "
        },
        {
          "text": "Топлевные Сепараторы"
        },
        {
          "text": "Воздушные"
        },
        {
          "text": "Салонные"
        }
      ]
    },
    {
      "title": "Подвеска и рама",
      "img": "img/accessories.png",
      "items": [
        {
          "text": "Масляные          "
        },
        {
          "text": "Топливные          "
        },
        {
          "text": "Топлевные Сепараторы"
        },
        {
          "text": "Воздушные"
        },
        {
          "text": "Салонные"
        }
      ]
    },
    {
      "title": "Электрика",
      "img": "img/accessories.png",
      "items": [
        {
          "text": "Масляные          "
        },
        {
          "text": "Топливные          "
        },
        {
          "text": "Топлевные Сепараторы"
        },
        {
          "text": "Воздушные"
        },
        {
          "text": "Салонные"
        }
      ]
    }
  ]
}